{
    "amazon": [
        "http:\/\/amazon.com",
        ""
    ],
    "artstation": [
        "http:\/\/artstation.com",
        ""
    ],
    "audiobookbay": [
        "http://audiobookbay.me/",
        ""
    ],
    "calculator": [
        "gnome-terminal -- ipython3 -i /bin/jtools_calc.py",
        ""
    ],
    "euler": [
        "https:\/\/projecteuler.net\/archives",
        ""
    ],
    "fsearch": [
        "fsearch",
        "wm_class_"
    ],
    "firefox": [
        "bash firefox",
        "wm_class_Navigator.firefox"
    ],
    "github": [
        "https:\/\/github.com\/Umbral-Tension?tab=repositories",
        ""
    ],
    "gmail": [
        "http:\/\/gmail.com",
        ""
    ],
    "joplin": [
        "/home/jeremy/.joplin/Joplin.AppImage",
        "wm_class_joplin.Joplin"
    ],
    "lichess": [
        "http:\/\/lichess.org",
        ""
    ],
    "localhost": [
        "http:\/\/localhost:8080",
        ""
    ],
    "python": [
        "python3",
        ""
    ],
    "random": [
        "http:\/\/reddit.com\/r\/random",
        ""
    ],
    "rhythmbox": [
        "rhythmbox",
        "wm_class_rhythmbox.Rhythmbox"
    ],
    "reddit": [
        "http:\/\/reddit.com",
        ""
    ],
    "redditsave": [
        "https:\/\/redditsave.com",
        ""
    ],
    "spotify": [
        "LD_PRELOAD=/usr/local/lib/spotify-adblock.so spotify",
        "wm_class_spotify.Spotify"
    ],
    "terminal": [
        "gnome-terminal",
        "wm_class_gnome-terminal-server.Gnome-terminal"
    ],
    "vscode": [
        "code",
        "wm_class_code.Code"
    ],
    "youtube": [
        "http:\/\/youtube.com",
        ""
    ]
}